chemscad/__init__.py
chemscad/__main__.py
chemscad/align_filters.py
chemscad/align_tops.py
chemscad/app_constants.py
chemscad/choice_module.py
chemscad/dashboard.py
chemscad/filtersettings.py
chemscad/functions.py
chemscad/help_info.py
chemscad/little_thread.py
chemscad/log.py
chemscad/main.py
chemscad/settings.py
chemscad/stl_viewer.py
chemscad/gui_modules/__init__.py
chemscad/gui_modules/connector_double_siphon/__init__.py
chemscad/gui_modules/connector_double_siphon/connector_double_siphon.py
chemscad/gui_modules/connector_double_siphon/draw.py
chemscad/gui_modules/connector_double_siphon/name.txt
chemscad/gui_modules/connector_siphon/__init__.py
chemscad/gui_modules/connector_siphon/connector_siphon.py
chemscad/gui_modules/connector_siphon/draw.py
chemscad/gui_modules/connector_siphon/name.txt
chemscad/gui_modules/connector_tube/__init__.py
chemscad/gui_modules/connector_tube/connector_tube.py
chemscad/gui_modules/connector_tube/draw.py
chemscad/gui_modules/connector_tube/name.txt
chemscad/gui_modules/module_double_filter_reactor/__init__.py
chemscad/gui_modules/module_double_filter_reactor/add_io_ffr.py
chemscad/gui_modules/module_double_filter_reactor/add_top_io_ffr.py
chemscad/gui_modules/module_double_filter_reactor/draw.py
chemscad/gui_modules/module_double_filter_reactor/module_double_filter_reactor.py
chemscad/gui_modules/module_double_filter_reactor/name.txt
chemscad/gui_modules/module_filter_reactor/__init__.py
chemscad/gui_modules/module_filter_reactor/add_io_fr.py
chemscad/gui_modules/module_filter_reactor/add_top_io_fr.py
chemscad/gui_modules/module_filter_reactor/draw.py
chemscad/gui_modules/module_filter_reactor/module_filter_reactor.py
chemscad/gui_modules/module_filter_reactor/name.txt
chemscad/gui_modules/module_floating_filter_reactor/__init__.py
chemscad/gui_modules/module_floating_filter_reactor/add_io_ffr.py
chemscad/gui_modules/module_floating_filter_reactor/add_top_io_ffr.py
chemscad/gui_modules/module_floating_filter_reactor/draw.py
chemscad-2.0.6.dist-info/LICENSE.txt
chemscad-2.0.6.dist-info/METADATA
chemscad-2.0.6.dist-info/WHEEL
chemscad-2.0.6.dist-info/entry_points.txt
chemscad-2.0.6.dist-info/top_level.txt
chemscad-2.0.6.dist-info/RECORD
