Metadata-Version: 2.1
Name: chemscad
Version: 2.0.6
Summary: GUI application for the creation of Reactionware.
Home-page: https://github.com/croningp/chemscad
Author: Cronin Group
Author-email: croningp.pypi@gmail.com
License: UNKNOWN
Platform: UNKNOWN
Classifier: Programming Language :: Python :: 3
Classifier: License :: OSI Approved :: GNU Affero General Public License v3 or later (AGPLv3+)
Classifier: Operating System :: OS Independent
Requires-Python: >=3.6
License-File: LICENSE.txt
Requires-Dist: appdirs (==1.4.4)
Requires-Dist: aspy.yaml (==1.3.0)
Requires-Dist: atomicwrites (==1.4.0)
Requires-Dist: attrs (==21.2.0)
Requires-Dist: backports.entry-points-selectable (==1.1.0)
Requires-Dist: bpyutils (==0.2.0)
Requires-Dist: business-rules (==1.0.1)
Requires-Dist: cached-property (==1.5.2)
Requires-Dist: ccad (==2.0)
Requires-Dist: certifi (==2021.5.30)
Requires-Dist: cfgv (==3.3.1)
Requires-Dist: colorama (==0.4.4)
Requires-Dist: cycler (==0.10.0)
Requires-Dist: Cython (==0.29.24)
Requires-Dist: decorator (==5.1.0)
Requires-Dist: distlib (==0.3.3)
Requires-Dist: euclid3 (==0.1)
Requires-Dist: filelock (==3.3.0)
Requires-Dist: freetype-py (==2.2.0)
Requires-Dist: future (==0.18.2)
Requires-Dist: graphviz (==0.17)
Requires-Dist: hsluv (==5.0.2)
Requires-Dist: identify (==2.3.0)
Requires-Dist: importlib-metadata (==4.8.1)
Requires-Dist: iniconfig (==1.1.1)
Requires-Dist: jedi (==0.18.0)
Requires-Dist: kiwisolver (==1.3.2)
Requires-Dist: lxml (==4.6.3)
Requires-Dist: matplotlib (==3.4.3)
Requires-Dist: more-itertools (==8.10.0)
Requires-Dist: mypy (==0.910)
Requires-Dist: mypy-extensions (==0.4.3)
Requires-Dist: networkx (==2.6.3)
Requires-Dist: nodeenv (==1.6.0)
Requires-Dist: numpy (==1.21.2)
Requires-Dist: packaging (==21.0)
Requires-Dist: parso (==0.8.2)
Requires-Dist: Pillow (==8.3.2)
Requires-Dist: pipupgrade (==1.10.1)
Requires-Dist: platformdirs (==2.4.0)
Requires-Dist: pluggy (==1.0.0)
Requires-Dist: pre-commit (==2.15.0)
Requires-Dist: prettytable (==0.7.2)
Requires-Dist: py (==1.10.0)
Requires-Dist: pyglet (==1.5.21)
Requires-Dist: pyparsing (==2.4.7)
Requires-Dist: pypng (==0.0.19)
Requires-Dist: PyQt5 (==5.15.4)
Requires-Dist: PyQt5-sip (==12.9.0)
Requires-Dist: pytest (==6.2.5)
Requires-Dist: python-dateutil (==2.8.2)
Requires-Dist: pytz (==2021.3)
Requires-Dist: PyYAML (==5.4.1)
Requires-Dist: regex (==2021.10.8)
Requires-Dist: scipy (==1.7.1)
Requires-Dist: sip (==6.2.0)
Requires-Dist: six (==1.16.0)
Requires-Dist: solidpython (==1.0.2)
Requires-Dist: toml (==0.10.2)
Requires-Dist: trimesh (==3.9.32)
Requires-Dist: typed-ast (==1.4.3)
Requires-Dist: typing-extensions (==3.10.0.2)
Requires-Dist: virtualenv (==20.8.1)
Requires-Dist: vispy (==0.6.6)
Requires-Dist: wcwidth (==0.2.5)
Requires-Dist: zipp (==3.6.0)
